LICENSE
MANIFEST.in
README.rst
requirements.txt
setup.py
qtmetabolabpy/__init__.py
qtmetabolabpy/__main__.py
qtmetabolabpy/qtMetaboLabPy.py
qtmetabolabpy.egg-info/PKG-INFO
qtmetabolabpy.egg-info/SOURCES.txt
qtmetabolabpy.egg-info/dependency_links.txt
qtmetabolabpy.egg-info/entry_points.txt
qtmetabolabpy.egg-info/requires.txt
qtmetabolabpy.egg-info/top_level.txt
qtmetabolabpy/bash/fix_pyside2
qtmetabolabpy/mlStarter/Icon
qtmetabolabpy/mlStarter/Contents/Info.plist
qtmetabolabpy/mlStarter/Contents/PkgInfo
qtmetabolabpy/mlStarter/Contents/Resources/AppIcon.icns
qtmetabolabpy/ui/metabolabpy_mainwindow.ui
qtmetabolabpy/web/basic2dprocessing.html
qtmetabolabpy/web/basicnmrdataprocessing.html
qtmetabolabpy/web/gui.html
qtmetabolabpy/web/index.html
qtmetabolabpy/web/metabolabpy.html
qtmetabolabpy/web/scripts.html
qtmetabolabpy/web/softwareinstall.html
qtmetabolabpy/web/tracing.html
qtmetabolabpy/web/css/HankenGrotesk_wght_.woff
qtmetabolabpy/web/css/HankenGrotesk_wght_.woff2
qtmetabolabpy/web/css/Roboto-Bold.woff
qtmetabolabpy/web/css/Roboto-Bold.woff2
qtmetabolabpy/web/css/Roboto-Light.woff
qtmetabolabpy/web/css/Roboto-Light.woff2
qtmetabolabpy/web/css/Roboto-Regular.woff
qtmetabolabpy/web/css/Roboto-Regular.woff2
qtmetabolabpy/web/css/Roboto-Thin.woff
qtmetabolabpy/web/css/Roboto-Thin.woff2
qtmetabolabpy/web/css/site.0d66f9.css
qtmetabolabpy/web/css/site.209df9.css
qtmetabolabpy/web/css/site.2eebff.css
qtmetabolabpy/web/css/site.359eb1.css
qtmetabolabpy/web/css/site.8b81ba.css
qtmetabolabpy/web/css/site.baa613.css
qtmetabolabpy/web/images/metabolabpy_dark_transparency-294.png
qtmetabolabpy/web/images/metabolabpy_dark_transparency-294.webp
qtmetabolabpy/web/images/metabolabpy_dark_transparency-588.png
qtmetabolabpy/web/images/metabolabpy_dark_transparency-588.webp
qtmetabolabpy/web/images/metabolismmap12-1200.png
qtmetabolabpy/web/images/metabolismmap12-1200.webp
qtmetabolabpy/web/images/metabolismmap12-1600.png
qtmetabolabpy/web/images/metabolismmap12-1600.webp
qtmetabolabpy/web/images/metabolismmap12-2000.png
qtmetabolabpy/web/images/metabolismmap12-2000.webp
qtmetabolabpy/web/images/metabolismmap12-2400.png
qtmetabolabpy/web/images/metabolismmap12-2400.webp
