Metadata-Version: 2.2
Name: qtmetabolabpy
Version: 0.9.71
Summary: Python package for data processing of NMR 1D and 2D metabolomics and metabolism tracing data
Home-page: https://github.com/ludwigc/qtmetabolabpy
Author: Christian Ludwig
Author-email: C.Ludwig@bham.ac.uk 
License: GPLv3
Keywords: Metabolomics,Tracing,NMR,Data Processing,13C
Platform: MacOS, Windows, UNIX
Classifier: Programming Language :: Python :: 3
Classifier: Programming Language :: Python :: 3.9
Classifier: Topic :: Scientific/Engineering :: Bio-Informatics
Classifier: Topic :: Scientific/Engineering :: Chemistry
Classifier: Topic :: Utilities
Classifier: License :: OSI Approved :: GNU General Public License v3 (GPLv3)
Classifier: Operating System :: OS Independent
License-File: LICENSE
Requires-Dist: PySide6
Requires-Dist: metabolabpy
Requires-Dist: numpy
Requires-Dist: scipy==1.13.1
Requires-Dist: matplotlib
Requires-Dist: pyautogui
Requires-Dist: qtmodern
Requires-Dist: xlsxwriter
Requires-Dist: multiprocess
Requires-Dist: darkdetect
Requires-Dist: pypdf2
Dynamic: author
Dynamic: author-email
Dynamic: classifier
Dynamic: description
Dynamic: home-page
Dynamic: keywords
Dynamic: license
Dynamic: platform
Dynamic: requires-dist
Dynamic: summary
